pytail/__init__.py
pytail/__main__.py
pytail/config.py
pytail/pytail.py
pytail-1.0.7.dist-info/DESCRIPTION.rst
pytail-1.0.7.dist-info/LICENSE.txt
pytail-1.0.7.dist-info/METADATA
pytail-1.0.7.dist-info/RECORD
pytail-1.0.7.dist-info/WHEEL
pytail-1.0.7.dist-info/metadata.json
pytail-1.0.7.dist-info/top_level.txt
