Metadata-Version: 2.0
Name: pytail
Version: 1.0.7
Summary: Tail files (logs) over TCP
Home-page: https://github.com/hmrodrigues/pytail
Author: Hugo Rodrigues
Author-email: me@hugorodrigues.net
License: BSD-3-Clause
Platform: UNKNOWN
Classifier: Development Status :: 5 - Production/Stable
Classifier: Environment :: No Input/Output (Daemon)
Classifier: Intended Audience :: System Administrators
Classifier: License :: OSI Approved :: BSD License
Classifier: Natural Language :: English
Classifier: Programming Language :: Python :: 3
Classifier: Programming Language :: Python :: 2
Classifier: Operating System :: Unix
Classifier: Topic :: System :: Logging
